JavaBianchengWentiChuyi/README.md
JavaBianchengWentiChuyi/__init__.py
JavaBianchengWentiChuyi/__main__.py
JavaBianchengWentiChuyi/file.epub
JavaBianchengWentiChuyi/index.html
JavaBianchengWentiChuyi/css/__init__.py
JavaBianchengWentiChuyi/css/annotations.css
JavaBianchengWentiChuyi/css/main.css
JavaBianchengWentiChuyi/css/normalize.css
JavaBianchengWentiChuyi/css/popup.css
JavaBianchengWentiChuyi/font/__init__.py
JavaBianchengWentiChuyi/font/fontello.eot
JavaBianchengWentiChuyi/font/fontello.svg
JavaBianchengWentiChuyi/font/fontello.ttf
JavaBianchengWentiChuyi/font/fontello.woff
JavaBianchengWentiChuyi/img/__init__.py
JavaBianchengWentiChuyi/img/annotator-glyph-sprite.png
JavaBianchengWentiChuyi/img/annotator-icon-sprite.png
JavaBianchengWentiChuyi/img/apple-touch-icon.png
JavaBianchengWentiChuyi/img/cancelfullscreen.png
JavaBianchengWentiChuyi/img/close.png
JavaBianchengWentiChuyi/img/fullscreen.png
JavaBianchengWentiChuyi/img/loader.gif
JavaBianchengWentiChuyi/img/menu-icon.png
JavaBianchengWentiChuyi/img/save.png
JavaBianchengWentiChuyi/img/saved.png
JavaBianchengWentiChuyi/img/settings-s.png
JavaBianchengWentiChuyi/img/settings.png
JavaBianchengWentiChuyi/img/star.png
JavaBianchengWentiChuyi/js/__init__.py
JavaBianchengWentiChuyi/js/epub.js
JavaBianchengWentiChuyi/js/epub.min.js
JavaBianchengWentiChuyi/js/epub.min.map
JavaBianchengWentiChuyi/js/hooks.min.js
JavaBianchengWentiChuyi/js/hooks.min.map
JavaBianchengWentiChuyi/js/reader.js
JavaBianchengWentiChuyi/js/reader.js.map
JavaBianchengWentiChuyi/js/reader.min.js
JavaBianchengWentiChuyi/js/reader.min.map
JavaBianchengWentiChuyi/js/hooks/__init__.py
JavaBianchengWentiChuyi/js/hooks/extensions/__init__.py
JavaBianchengWentiChuyi/js/hooks/extensions/highlight.js
JavaBianchengWentiChuyi/js/libs/__init__.py
JavaBianchengWentiChuyi/js/libs/jquery.min.js
JavaBianchengWentiChuyi/js/libs/localforage.min.js
JavaBianchengWentiChuyi/js/libs/screenfull.js
JavaBianchengWentiChuyi/js/libs/screenfull.min.js
java_biancheng_wenti_chuyi-2024.3.5.0.dist-info/METADATA
java_biancheng_wenti_chuyi-2024.3.5.0.dist-info/WHEEL
java_biancheng_wenti_chuyi-2024.3.5.0.dist-info/entry_points.txt
java_biancheng_wenti_chuyi-2024.3.5.0.dist-info/top_level.txt
java_biancheng_wenti_chuyi-2024.3.5.0.dist-info/RECORD
